guards/__init__.py
guards/default.py
guards/null.py
guards/singleton.py
guards/unwrap.py
guards-1.1.4.dist-info/LICENSE
guards-1.1.4.dist-info/WHEEL
guards-1.1.4.dist-info/METADATA
guards-1.1.4.dist-info/RECORD
