Metadata-Version: 2.1
Name: guards
Version: 1.1.4
Summary: Tools for guarding Defaults, Null and creating Singletons.
Home-page: https://github.com/xyngular/py-guards
License: MIT
Keywords: singleton,type,guards,default,null
Author: Josh Orr
Author-email: josh@orr.blue
Requires-Python: >=3.8,<4.0
Classifier: License :: OSI Approved :: MIT License
Classifier: Programming Language :: Python :: 3
Classifier: Programming Language :: Python :: 3.8
Classifier: Programming Language :: Python :: 3.9
Classifier: Programming Language :: Python :: 3.10
Classifier: Programming Language :: Python :: 3.11
Classifier: Topic :: Software Development :: Libraries :: Python Modules
Requires-Dist: typing-inspect (>=0.8.0,<0.9.0)
Project-URL: Repository, https://github.com/xyngular/py-guards
